{
  "run_id": "miniweek_vwap_bounce_5m_solo_12w_vwap_bounce_5m_solo_12w_sep_w2",
  "n_setups": 20,
  "components": {
    "liquidity_sweep_score": {
      "min": 0.3,
      "median": 0.3,
      "p90": 0.3
    },
    "bos_strength_score": {
      "min": 0.0,
      "median": 0.2922307369104661,
      "p90": 0.4596710711956734
    },
    "fvg_quality_score": {
      "min": 0.6625594668975399,
      "median": 0.6625594668975399,
      "p90": 0.6625594668975399
    },
    "pattern_quality_score": {
      "min": 0.95,
      "median": 1.0,
      "p90": 1.0
    }
  },
  "flags": {
    "sweep_detected_pct": 0.0,
    "bos_detected_pct": 95.0,
    "fvg_detected_pct": 100.0,
    "pattern_detected_pct": 100.0
  },
  "quality_distribution": {
    "A+": 20
  }
}