{
  "run_id": "agg_Sep15-19",
  "total_trades": 48,
  "score_count": 48,
  "score_min": 0.16987405146753706,
  "score_max": 1.0,
  "score_mean": 0.6780492383253893,
  "grade_counts": {
    "A+": 34,
    "A": 8,
    "B": 1,
    "C": 5,
    "UNKNOWN": 0
  },
  "thresholds_snapshot": {
    "BOS_Scalp_1m": {
      "count": 15,
      "thresholds": {
        "A_plus": 0.5,
        "A": 0.01,
        "B": 0.0
      }
    },
    "NY_Open_Reversal": {
      "count": 10,
      "thresholds": {
        "A_plus": 0.8,
        "A": 0.65,
        "B": 0.5
      }
    },
    "Engulfing_Bar_V056": {
      "count": 10,
      "thresholds": {
        "A_plus": 0.5,
        "A": 0.01,
        "B": 0.0
      }
    }
  },
  "sample_first_5_trades": [
    {
      "trade_id": "d2b6b124-577b-4740-87ba-a01c1753af09",
      "playbook": "NY_Open_Reversal",
      "quality": "C",
      "match_score": 0.23012541826655222,
      "match_grade": "C",
      "grade_thresholds": {
        "A_plus": 0.8,
        "A": 0.65,
        "B": 0.5
      },
      "score_scale_hint": "0-1"
    },
    {
      "trade_id": "b79ff419-63e9-49cb-86cb-48b3a25d4bcc",
      "playbook": "NY_Open_Reversal",
      "quality": "C",
      "match_score": 0.23857095996803074,
      "match_grade": "C",
      "grade_thresholds": {
        "A_plus": 0.8,
        "A": 0.65,
        "B": 0.5
      },
      "score_scale_hint": "0-1"
    },
    {
      "trade_id": "a3d0017b-d102-4461-814f-0e379539a92b",
      "playbook": "VWAP_Bounce_5m",
      "quality": "A+",
      "match_score": 0.8,
      "match_grade": "A+",
      "grade_thresholds": {
        "A_plus": 0.5,
        "A": 0.01,
        "B": 0.0
      },
      "score_scale_hint": "0-1"
    },
    {
      "trade_id": "752618fa-97f7-463e-bfad-216e853ea3e6",
      "playbook": "BOS_Scalp_1m",
      "quality": "A",
      "match_score": 0.231205359180934,
      "match_grade": "A",
      "grade_thresholds": {
        "A_plus": 0.5,
        "A": 0.01,
        "B": 0.0
      },
      "score_scale_hint": "0-1"
    },
    {
      "trade_id": "8b28e97f-8953-468a-a62a-789b969f29f1",
      "playbook": "Engulfing_Bar_V056",
      "quality": "A+",
      "match_score": 1.0,
      "match_grade": "A+",
      "grade_thresholds": {
        "A_plus": 0.5,
        "A": 0.01,
        "B": 0.0
      },
      "score_scale_hint": "0-1"
    }
  ],
  "reason_if_empty": null,
  "diagnostic": null,
  "diagnostic_data": null,
  "all_trades": [
    {
      "trade_id": "d2b6b124-577b-4740-87ba-a01c1753af09",
      "playbook": "NY_Open_Reversal",
      "quality": "C",
      "match_score": 0.23012541826655222,
      "match_grade": "C",
      "grade_thresholds": {
        "A_plus": 0.8,
        "A": 0.65,
        "B": 0.5
      },
      "score_scale_hint": "0-1"
    },
    {
      "trade_id": "b79ff419-63e9-49cb-86cb-48b3a25d4bcc",
      "playbook": "NY_Open_Reversal",
      "quality": "C",
      "match_score": 0.23857095996803074,
      "match_grade": "C",
      "grade_thresholds": {
        "A_plus": 0.8,
        "A": 0.65,
        "B": 0.5
      },
      "score_scale_hint": "0-1"
    },
    {
      "trade_id": "a3d0017b-d102-4461-814f-0e379539a92b",
      "playbook": "VWAP_Bounce_5m",
      "quality": "A+",
      "match_score": 0.8,
      "match_grade": "A+",
      "grade_thresholds": {
        "A_plus": 0.5,
        "A": 0.01,
        "B": 0.0
      },
      "score_scale_hint": "0-1"
    },
    {
      "trade_id": "752618fa-97f7-463e-bfad-216e853ea3e6",
      "playbook": "BOS_Scalp_1m",
      "quality": "A",
      "match_score": 0.231205359180934,
      "match_grade": "A",
      "grade_thresholds": {
        "A_plus": 0.5,
        "A": 0.01,
        "B": 0.0
      },
      "score_scale_hint": "0-1"
    },
    {
      "trade_id": "8b28e97f-8953-468a-a62a-789b969f29f1",
      "playbook": "Engulfing_Bar_V056",
      "quality": "A+",
      "match_score": 1.0,
      "match_grade": "A+",
      "grade_thresholds": {
        "A_plus": 0.5,
        "A": 0.01,
        "B": 0.0
      },
      "score_scale_hint": "0-1"
    },
    {
      "trade_id": "d2bcc342-6941-4dd5-97f7-4dbe24fb0784",
      "playbook": "BOS_Scalp_1m",
      "quality": "A",
      "match_score": 0.17189828103281685,
      "match_grade": "A",
      "grade_thresholds": {
        "A_plus": 0.5,
        "A": 0.01,
        "B": 0.0
      },
      "score_scale_hint": "0-1"
    },
    {
      "trade_id": "5dcffb0d-6d10-48d0-a93f-e02a10929db0",
      "playbook": "BOS_Scalp_1m",
      "quality": "A",
      "match_score": 0.16987405146753706,
      "match_grade": "A",
      "grade_thresholds": {
        "A_plus": 0.5,
        "A": 0.01,
        "B": 0.0
      },
      "score_scale_hint": "0-1"
    },
    {
      "trade_id": "75f13a5a-d219-4d28-a217-cecf8fa5ecc6",
      "playbook": "Engulfing_Bar_V056",
      "quality": "A+",
      "match_score": 1.0,
      "match_grade": "A+",
      "grade_thresholds": {
        "A_plus": 0.5,
        "A": 0.01,
        "B": 0.0
      },
      "score_scale_hint": "0-1"
    },
    {
      "trade_id": "6460f928-dfeb-468c-9b46-755b9fa59557",
      "playbook": "ORB_Breakout_5m",
      "quality": "A+",
      "match_score": 0.8,
      "match_grade": "A+",
      "grade_thresholds": {
        "A_plus": 0.5,
        "A": 0.01,
        "B": 0.0
      },
      "score_scale_hint": "0-1"
    },
    {
      "trade_id": "d0864393-fa67-4bd7-b17e-32cf77604846",
      "playbook": "EMA_Cross_5m",
      "quality": "A+",
      "match_score": 0.8,
      "match_grade": "A+",
      "grade_thresholds": {
        "A_plus": 0.5,
        "A": 0.01,
        "B": 0.0
      },
      "score_scale_hint": "0-1"
    },
    {
      "trade_id": "0e882f57-6bd8-4a95-9cce-d7b8e2b0e21c",
      "playbook": "EMA_Cross_5m",
      "quality": "A+",
      "match_score": 0.8,
      "match_grade": "A+",
      "grade_thresholds": {
        "A_plus": 0.5,
        "A": 0.01,
        "B": 0.0
      },
      "score_scale_hint": "0-1"
    },
    {
      "trade_id": "91d3bb9c-b447-4b9f-ad7f-7959c904f58d",
      "playbook": "Engulfing_Bar_V056",
      "quality": "A+",
      "match_score": 1.0,
      "match_grade": "A+",
      "grade_thresholds": {
        "A_plus": 0.5,
        "A": 0.01,
        "B": 0.0
      },
      "score_scale_hint": "0-1"
    },
    {
      "trade_id": "5235dcfe-c025-4447-8da9-8d81bdd15b78",
      "playbook": "BOS_Scalp_1m",
      "quality": "A+",
      "match_score": 0.582202350676085,
      "match_grade": "A+",
      "grade_thresholds": {
        "A_plus": 0.5,
        "A": 0.01,
        "B": 0.0
      },
      "score_scale_hint": "0-1"
    },
    {
      "trade_id": "a9ee1f2b-94e5-408b-83ea-db36c1ba5af2",
      "playbook": "BOS_Scalp_1m",
      "quality": "A+",
      "match_score": 0.5517897816668302,
      "match_grade": "A+",
      "grade_thresholds": {
        "A_plus": 0.5,
        "A": 0.01,
        "B": 0.0
      },
      "score_scale_hint": "0-1"
    },
    {
      "trade_id": "3d983d9a-38bd-4607-a67b-4a2319d00a4f",
      "playbook": "BOS_Scalp_1m",
      "quality": "A+",
      "match_score": 0.6184414985927988,
      "match_grade": "A+",
      "grade_thresholds": {
        "A_plus": 0.5,
        "A": 0.01,
        "B": 0.0
      },
      "score_scale_hint": "0-1"
    },
    {
      "trade_id": "e547a700-a0e1-4934-86bf-81714b7810c6",
      "playbook": "Engulfing_Bar_V056",
      "quality": "A+",
      "match_score": 1.0,
      "match_grade": "A+",
      "grade_thresholds": {
        "A_plus": 0.5,
        "A": 0.01,
        "B": 0.0
      },
      "score_scale_hint": "0-1"
    },
    {
      "trade_id": "7234fecf-1f79-4913-b363-887d11145227",
      "playbook": "VWAP_Bounce_5m",
      "quality": "A+",
      "match_score": 0.8,
      "match_grade": "A+",
      "grade_thresholds": {
        "A_plus": 0.5,
        "A": 0.01,
        "B": 0.0
      },
      "score_scale_hint": "0-1"
    },
    {
      "trade_id": "2f3b5290-0686-4dbd-b16e-2bf43a73bcea",
      "playbook": "ORB_Breakout_5m",
      "quality": "A+",
      "match_score": 0.8,
      "match_grade": "A+",
      "grade_thresholds": {
        "A_plus": 0.5,
        "A": 0.01,
        "B": 0.0
      },
      "score_scale_hint": "0-1"
    },
    {
      "trade_id": "13c40eed-a9cc-4074-b807-d97b5316a3f6",
      "playbook": "ORB_Breakout_5m",
      "quality": "A+",
      "match_score": 0.8,
      "match_grade": "A+",
      "grade_thresholds": {
        "A_plus": 0.5,
        "A": 0.01,
        "B": 0.0
      },
      "score_scale_hint": "0-1"
    },
    {
      "trade_id": "927dc8e9-b17d-484c-b780-dc4984d18ad2",
      "playbook": "VWAP_Bounce_5m",
      "quality": "A+",
      "match_score": 0.8,
      "match_grade": "A+",
      "grade_thresholds": {
        "A_plus": 0.5,
        "A": 0.01,
        "B": 0.0
      },
      "score_scale_hint": "0-1"
    },
    {
      "trade_id": "5b26eb78-558c-4b45-b2f1-2bb1fbc8c0c0",
      "playbook": "VWAP_Bounce_5m",
      "quality": "A+",
      "match_score": 0.8,
      "match_grade": "A+",
      "grade_thresholds": {
        "A_plus": 0.5,
        "A": 0.01,
        "B": 0.0
      },
      "score_scale_hint": "0-1"
    },
    {
      "trade_id": "abbe237c-ffec-474e-a253-602f3ccae323",
      "playbook": "Engulfing_Bar_V056",
      "quality": "A+",
      "match_score": 1.0,
      "match_grade": "A+",
      "grade_thresholds": {
        "A_plus": 0.5,
        "A": 0.01,
        "B": 0.0
      },
      "score_scale_hint": "0-1"
    },
    {
      "trade_id": "5ad70d3e-ea17-4c90-868e-241888e7a0c8",
      "playbook": "Engulfing_Bar_V056",
      "quality": "A+",
      "match_score": 1.0,
      "match_grade": "A+",
      "grade_thresholds": {
        "A_plus": 0.5,
        "A": 0.01,
        "B": 0.0
      },
      "score_scale_hint": "0-1"
    },
    {
      "trade_id": "6f886385-1236-4e31-894b-c0734e0f242e",
      "playbook": "BOS_Scalp_1m",
      "quality": "A+",
      "match_score": 0.6408643824123326,
      "match_grade": "A+",
      "grade_thresholds": {
        "A_plus": 0.5,
        "A": 0.01,
        "B": 0.0
      },
      "score_scale_hint": "0-1"
    },
    {
      "trade_id": "2ae421e5-fc4c-4d10-9bcd-b0b3628cc1cf",
      "playbook": "BOS_Scalp_1m",
      "quality": "A+",
      "match_score": 0.6286517112819355,
      "match_grade": "A+",
      "grade_thresholds": {
        "A_plus": 0.5,
        "A": 0.01,
        "B": 0.0
      },
      "score_scale_hint": "0-1"
    },
    {
      "trade_id": "ff54ef01-e8f4-4869-830a-960f9668ff7d",
      "playbook": "BOS_Scalp_1m",
      "quality": "A+",
      "match_score": 0.650112740920868,
      "match_grade": "A+",
      "grade_thresholds": {
        "A_plus": 0.5,
        "A": 0.01,
        "B": 0.0
      },
      "score_scale_hint": "0-1"
    },
    {
      "trade_id": "aa7e1d7a-44ed-4603-a88f-664763360446",
      "playbook": "NY_Open_Reversal",
      "quality": "C",
      "match_score": 0.202653005591175,
      "match_grade": "C",
      "grade_thresholds": {
        "A_plus": 0.8,
        "A": 0.65,
        "B": 0.5
      },
      "score_scale_hint": "0-1"
    },
    {
      "trade_id": "d57bcc87-433e-4bb4-be4f-a967bcb8eaf4",
      "playbook": "NY_Open_Reversal",
      "quality": "B",
      "match_score": 0.502653005591175,
      "match_grade": "B",
      "grade_thresholds": {
        "A_plus": 0.8,
        "A": 0.65,
        "B": 0.5
      },
      "score_scale_hint": "0-1"
    },
    {
      "trade_id": "b64e8367-86f9-4ad7-94b9-8b0b9236f9e6",
      "playbook": "NY_Open_Reversal",
      "quality": "C",
      "match_score": 0.45327714559445204,
      "match_grade": "C",
      "grade_thresholds": {
        "A_plus": 0.8,
        "A": 0.65,
        "B": 0.5
      },
      "score_scale_hint": "0-1"
    },
    {
      "trade_id": "06110b9d-bd73-4df4-8e98-11c71cb58baf",
      "playbook": "NY_Open_Reversal",
      "quality": "C",
      "match_score": 0.49707203030901426,
      "match_grade": "C",
      "grade_thresholds": {
        "A_plus": 0.8,
        "A": 0.65,
        "B": 0.5
      },
      "score_scale_hint": "0-1"
    },
    {
      "trade_id": "cba9c52e-5c4d-418a-a242-57f34a65e9b9",
      "playbook": "Liquidity_Raid_V056",
      "quality": "A+",
      "match_score": 0.7246448648975405,
      "match_grade": "A+",
      "grade_thresholds": {
        "A_plus": 0.5,
        "A": 0.01,
        "B": 0.0
      },
      "score_scale_hint": "0-1"
    },
    {
      "trade_id": "3b9d28c4-0631-4d7b-a463-e780184b6355",
      "playbook": "Liquidity_Raid_V056",
      "quality": "A",
      "match_score": 0.31120994024463017,
      "match_grade": "A",
      "grade_thresholds": {
        "A_plus": 0.5,
        "A": 0.01,
        "B": 0.0
      },
      "score_scale_hint": "0-1"
    },
    {
      "trade_id": "c9022185-4045-4960-b10f-f0aa314b28c0",
      "playbook": "Engulfing_Bar_V056",
      "quality": "A+",
      "match_score": 1.0,
      "match_grade": "A+",
      "grade_thresholds": {
        "A_plus": 0.5,
        "A": 0.01,
        "B": 0.0
      },
      "score_scale_hint": "0-1"
    },
    {
      "trade_id": "0480076b-9a56-458b-aac3-2495d842f2b5",
      "playbook": "BOS_Scalp_1m",
      "quality": "A+",
      "match_score": 0.5785846800912117,
      "match_grade": "A+",
      "grade_thresholds": {
        "A_plus": 0.5,
        "A": 0.01,
        "B": 0.0
      },
      "score_scale_hint": "0-1"
    },
    {
      "trade_id": "2fd1d39c-2398-40ee-8723-7ebffa74a831",
      "playbook": "Engulfing_Bar_V056",
      "quality": "A+",
      "match_score": 1.0,
      "match_grade": "A+",
      "grade_thresholds": {
        "A_plus": 0.5,
        "A": 0.01,
        "B": 0.0
      },
      "score_scale_hint": "0-1"
    },
    {
      "trade_id": "06d41a4b-8686-4b71-8ede-28b297757861",
      "playbook": "BOS_Scalp_1m",
      "quality": "A+",
      "match_score": 0.5308012697987963,
      "match_grade": "A+",
      "grade_thresholds": {
        "A_plus": 0.5,
        "A": 0.01,
        "B": 0.0
      },
      "score_scale_hint": "0-1"
    },
    {
      "trade_id": "584b3b02-784e-4938-96f1-689cd844a1a0",
      "playbook": "BOS_Scalp_1m",
      "quality": "A+",
      "match_score": 0.5532561759704162,
      "match_grade": "A+",
      "grade_thresholds": {
        "A_plus": 0.5,
        "A": 0.01,
        "B": 0.0
      },
      "score_scale_hint": "0-1"
    },
    {
      "trade_id": "48279d4c-8b38-4d36-b2ed-b533a5be1a81",
      "playbook": "NY_Open_Reversal",
      "quality": "A",
      "match_score": 0.6995266361677934,
      "match_grade": "A",
      "grade_thresholds": {
        "A_plus": 0.8,
        "A": 0.65,
        "B": 0.5
      },
      "score_scale_hint": "0-1"
    },
    {
      "trade_id": "a0647aa4-9a0a-49f9-acca-f4e233308e7d",
      "playbook": "Engulfing_Bar_V056",
      "quality": "A+",
      "match_score": 1.0,
      "match_grade": "A+",
      "grade_thresholds": {
        "A_plus": 0.5,
        "A": 0.01,
        "B": 0.0
      },
      "score_scale_hint": "0-1"
    },
    {
      "trade_id": "7cbfe339-21d3-4422-9076-7ddb06269aee",
      "playbook": "BOS_Scalp_1m",
      "quality": "A+",
      "match_score": 0.5587616259372983,
      "match_grade": "A+",
      "grade_thresholds": {
        "A_plus": 0.5,
        "A": 0.01,
        "B": 0.0
      },
      "score_scale_hint": "0-1"
    },
    {
      "trade_id": "ba7dae05-5b8f-4843-b940-45191aa811a7",
      "playbook": "BOS_Scalp_1m",
      "quality": "A+",
      "match_score": 0.5523386863018585,
      "match_grade": "A+",
      "grade_thresholds": {
        "A_plus": 0.5,
        "A": 0.01,
        "B": 0.0
      },
      "score_scale_hint": "0-1"
    },
    {
      "trade_id": "1344d641-4eed-470c-a28a-1fe3f3e921b7",
      "playbook": "BOS_Scalp_1m",
      "quality": "A+",
      "match_score": 0.6413538139528958,
      "match_grade": "A+",
      "grade_thresholds": {
        "A_plus": 0.5,
        "A": 0.01,
        "B": 0.0
      },
      "score_scale_hint": "0-1"
    },
    {
      "trade_id": "77019865-37a2-45f9-8d61-69b4b224b1c5",
      "playbook": "Engulfing_Bar_V056",
      "quality": "A+",
      "match_score": 1.0,
      "match_grade": "A+",
      "grade_thresholds": {
        "A_plus": 0.5,
        "A": 0.01,
        "B": 0.0
      },
      "score_scale_hint": "0-1"
    },
    {
      "trade_id": "c236c0ac-5f15-4694-bc5b-cc73228e6256",
      "playbook": "ORB_Breakout_5m",
      "quality": "A+",
      "match_score": 0.8,
      "match_grade": "A+",
      "grade_thresholds": {
        "A_plus": 0.5,
        "A": 0.01,
        "B": 0.0
      },
      "score_scale_hint": "0-1"
    },
    {
      "trade_id": "150217c8-682a-4633-85bf-9980dc961b5f",
      "playbook": "NY_Open_Reversal",
      "quality": "A",
      "match_score": 0.7198903121196442,
      "match_grade": "A",
      "grade_thresholds": {
        "A_plus": 0.8,
        "A": 0.65,
        "B": 0.5
      },
      "score_scale_hint": "0-1"
    },
    {
      "trade_id": "9d262019-07fc-48fe-9ca1-e64bf661915a",
      "playbook": "RSI_MeanRev_5m",
      "quality": "A+",
      "match_score": 0.8690125394889222,
      "match_grade": "A+",
      "grade_thresholds": {
        "A_plus": 0.5,
        "A": 0.01,
        "B": 0.0
      },
      "score_scale_hint": "0-1"
    },
    {
      "trade_id": "addbb942-1577-4687-b38a-fe86cb33fee6",
      "playbook": "NY_Open_Reversal",
      "quality": "A",
      "match_score": 0.6799999999999999,
      "match_grade": "A",
      "grade_thresholds": {
        "A_plus": 0.8,
        "A": 0.65,
        "B": 0.5
      },
      "score_scale_hint": "0-1"
    },
    {
      "trade_id": "db38386b-c1e9-46bd-88c8-b9819e9831c3",
      "playbook": "NY_Open_Reversal",
      "quality": "A",
      "match_score": 0.7575911720951445,
      "match_grade": "A",
      "grade_thresholds": {
        "A_plus": 0.8,
        "A": 0.65,
        "B": 0.5
      },
      "score_scale_hint": "0-1"
    }
  ]
}