{
  "2025-10-27": {
    "SPY": {
      "raw": {},
      "after_mode": {},
      "trades_executed": 10,
      "minutes_with_A_plus": 0,
      "sessions": {},
      "trades_by_playbook": {
        "News_Fade": {
          "count": 1,
          "total_r": 0.12448193547447152
        },
        "Engulfing_Bar_V056": {
          "count": 2,
          "total_r": 0.25823143111823116
        },
        "BOS_Scalp_1m": {
          "count": 3,
          "total_r": 0.4078283573892856
        },
        "Liquidity_Raid_V056": {
          "count": 2,
          "total_r": 0.22937852770904724
        },
        "ORB_Breakout_5m": {
          "count": 2,
          "total_r": 0.09244267834816247
        }
      }
    }
  },
  "2025-10-28": {
    "SPY": {
      "raw": {},
      "after_mode": {},
      "trades_executed": 11,
      "minutes_with_A_plus": 0,
      "sessions": {},
      "trades_by_playbook": {
        "News_Fade": {
          "count": 1,
          "total_r": -1.0
        },
        "Engulfing_Bar_V056": {
          "count": 2,
          "total_r": -1.5137173461580034
        },
        "NY_Open_Reversal": {
          "count": 3,
          "total_r": 1.9078050319043383
        },
        "BOS_Scalp_1m": {
          "count": 3,
          "total_r": -2.5162860152979523
        },
        "ORB_Breakout_5m": {
          "count": 2,
          "total_r": -0.2442624559455078
        }
      }
    }
  },
  "2025-10-29": {
    "SPY": {
      "raw": {},
      "after_mode": {},
      "trades_executed": 15,
      "minutes_with_A_plus": 0,
      "sessions": {},
      "trades_by_playbook": {
        "News_Fade": {
          "count": 1,
          "total_r": 0.1395478649176853
        },
        "NY_Open_Reversal": {
          "count": 2,
          "total_r": -0.23274996120835967
        },
        "Liquidity_Raid_V056": {
          "count": 2,
          "total_r": -1.3175528420979354
        },
        "Engulfing_Bar_V056": {
          "count": 2,
          "total_r": -0.5311059934297542
        },
        "VWAP_Bounce_5m": {
          "count": 1,
          "total_r": -0.3741807848905103
        },
        "BOS_Scalp_1m": {
          "count": 3,
          "total_r": -0.9167731164744662
        },
        "ORB_Breakout_5m": {
          "count": 1,
          "total_r": 0.20149610860643358
        },
        "FVG_Scalp_1m": {
          "count": 3,
          "total_r": 2.7505056016038307
        }
      }
    }
  },
  "2025-10-30": {
    "SPY": {
      "raw": {},
      "after_mode": {},
      "trades_executed": 10,
      "minutes_with_A_plus": 0,
      "sessions": {},
      "trades_by_playbook": {
        "News_Fade": {
          "count": 1,
          "total_r": -0.30495514927926304
        },
        "Engulfing_Bar_V056": {
          "count": 2,
          "total_r": -0.6159834610803996
        },
        "BOS_Scalp_1m": {
          "count": 3,
          "total_r": -1.136554872192782
        },
        "FVG_Fill_V065": {
          "count": 1,
          "total_r": 0.4245592431174791
        },
        "NY_Open_Reversal": {
          "count": 1,
          "total_r": -1.0
        },
        "VWAP_Bounce_5m": {
          "count": 1,
          "total_r": 0.4688088412736355
        },
        "RSI_MeanRev_5m": {
          "count": 1,
          "total_r": 1.4999999999999583
        }
      }
    }
  },
  "2025-10-31": {
    "SPY": {
      "raw": {},
      "after_mode": {},
      "trades_executed": 15,
      "minutes_with_A_plus": 0,
      "sessions": {},
      "trades_by_playbook": {
        "NY_Open_Reversal": {
          "count": 4,
          "total_r": 1.7523389961661493
        },
        "News_Fade": {
          "count": 1,
          "total_r": 0.0
        },
        "Engulfing_Bar_V056": {
          "count": 2,
          "total_r": -0.3957076684984703
        },
        "BOS_Scalp_1m": {
          "count": 3,
          "total_r": -0.5972993056871785
        },
        "VWAP_Bounce_5m": {
          "count": 3,
          "total_r": -2.6534039565695213
        },
        "RSI_MeanRev_5m": {
          "count": 1,
          "total_r": 0.08415106213276206
        },
        "ORB_Breakout_5m": {
          "count": 1,
          "total_r": 0.0
        }
      }
    }
  }
}