{
  "run_id": "job_verify_sprint3",
  "rows": [
    {
      "playbook": "Morning_Trap_Reversal",
      "setups": 68,
      "avg_indecision_ratio": 0.26864283125840177,
      "avg_directional_conviction": 0.8835063437139562,
      "neutral_dominant_ratio": 0.0,
      "avg_structure_quality_score": 0.26884452100667006,
      "regime_trend_ratio": 0.0,
      "regime_range_ratio": 0.35294117647058826,
      "regime_chop_ratio": 0.6470588235294118
    },
    {
      "playbook": "Liquidity_Sweep_Scalp",
      "setups": 65,
      "avg_indecision_ratio": 0.24642794312419003,
      "avg_directional_conviction": 0.8781297134238311,
      "neutral_dominant_ratio": 0.0,
      "avg_structure_quality_score": 0.2723677790027438,
      "regime_trend_ratio": 0.0,
      "regime_range_ratio": 0.3230769230769231,
      "regime_chop_ratio": 0.676923076923077
    },
    {
      "playbook": "NY_Lunch_Breakout_Reprice",
      "setups": 40,
      "avg_indecision_ratio": 0.0,
      "avg_directional_conviction": 0.5944945182374025,
      "neutral_dominant_ratio": 0.0,
      "avg_structure_quality_score": 0.2998958992199031,
      "regime_trend_ratio": 0.0,
      "regime_range_ratio": 0.0,
      "regime_chop_ratio": 1.0
    },
    {
      "playbook": "London_Reversal_Into_NY",
      "setups": 40,
      "avg_indecision_ratio": 0.0,
      "avg_directional_conviction": 0.5944945182374025,
      "neutral_dominant_ratio": 0.0,
      "avg_structure_quality_score": 0.2998958992199031,
      "regime_trend_ratio": 0.0,
      "regime_range_ratio": 0.0,
      "regime_chop_ratio": 1.0
    },
    {
      "playbook": "IFVG_Flip_Scalp",
      "setups": 40,
      "avg_indecision_ratio": 0.0,
      "avg_directional_conviction": 0.5944945182374025,
      "neutral_dominant_ratio": 0.0,
      "avg_structure_quality_score": 0.2998958992199031,
      "regime_trend_ratio": 0.0,
      "regime_range_ratio": 0.0,
      "regime_chop_ratio": 1.0
    },
    {
      "playbook": "SMT_Divergence_Scalp",
      "setups": 40,
      "avg_indecision_ratio": 0.0,
      "avg_directional_conviction": 0.5944945182374025,
      "neutral_dominant_ratio": 0.0,
      "avg_structure_quality_score": 0.2998958992199031,
      "regime_trend_ratio": 0.0,
      "regime_range_ratio": 0.0,
      "regime_chop_ratio": 1.0
    },
    {
      "playbook": "Close_Reversion_Scalp",
      "setups": 40,
      "avg_indecision_ratio": 0.0,
      "avg_directional_conviction": 0.5944945182374025,
      "neutral_dominant_ratio": 0.0,
      "avg_structure_quality_score": 0.2998958992199031,
      "regime_trend_ratio": 0.0,
      "regime_range_ratio": 0.0,
      "regime_chop_ratio": 1.0
    },
    {
      "playbook": "VWAP_Failure_Reversal_SAFE",
      "setups": 40,
      "avg_indecision_ratio": 0.0,
      "avg_directional_conviction": 0.5944945182374025,
      "neutral_dominant_ratio": 0.0,
      "avg_structure_quality_score": 0.2998958992199031,
      "regime_trend_ratio": 0.0,
      "regime_range_ratio": 0.0,
      "regime_chop_ratio": 1.0
    },
    {
      "playbook": "Midday_Compression_Break_SAFE",
      "setups": 40,
      "avg_indecision_ratio": 0.0,
      "avg_directional_conviction": 0.5944945182374025,
      "neutral_dominant_ratio": 0.0,
      "avg_structure_quality_score": 0.2998958992199031,
      "regime_trend_ratio": 0.0,
      "regime_range_ratio": 0.0,
      "regime_chop_ratio": 1.0
    },
    {
      "playbook": "DAY_Aplus_1_Liquidity_Sweep_OB_Retest",
      "setups": 40,
      "avg_indecision_ratio": 0.0,
      "avg_directional_conviction": 0.5944945182374025,
      "neutral_dominant_ratio": 0.0,
      "avg_structure_quality_score": 0.2998958992199031,
      "regime_trend_ratio": 0.0,
      "regime_range_ratio": 0.0,
      "regime_chop_ratio": 1.0
    },
    {
      "playbook": "SCALP_Aplus_1_Mini_FVG_Retest_NY_Open",
      "setups": 40,
      "avg_indecision_ratio": 0.0,
      "avg_directional_conviction": 0.5944945182374025,
      "neutral_dominant_ratio": 0.0,
      "avg_structure_quality_score": 0.2998958992199031,
      "regime_trend_ratio": 0.0,
      "regime_range_ratio": 0.0,
      "regime_chop_ratio": 1.0
    },
    {
      "playbook": "Session_Open_Scalp",
      "setups": 10,
      "avg_indecision_ratio": 0.0,
      "avg_directional_conviction": 0.8666666666666668,
      "neutral_dominant_ratio": 0.0,
      "avg_structure_quality_score": 0.33799999999999997,
      "regime_trend_ratio": 0.0,
      "regime_range_ratio": 0.0,
      "regime_chop_ratio": 1.0
    }
  ]
}